resampy/__init__.py
resampy/core.py
resampy/filters.py
resampy/interpn.py
resampy/version.py
resampy/data/kaiser_best.npz
resampy/data/kaiser_fast.npz
resampy-0.4.3.dist-info/LICENSE.md
resampy-0.4.3.dist-info/METADATA
resampy-0.4.3.dist-info/WHEEL
resampy-0.4.3.dist-info/top_level.txt
resampy-0.4.3.dist-info/RECORD
