Metadata-Version: 2.1
Name: resampy
Version: 0.4.3
Summary: Efficient signal resampling
Home-page: https://github.com/bmcfee/resampy
Download-URL: https://github.com/bmcfee/resampy/releases
Author: Brian McFee
Author-email: brian.mcfee@nyu.edu
License: ISC
Classifier: License :: OSI Approved :: ISC License (ISCL)
Classifier: Programming Language :: Python
Classifier: Development Status :: 3 - Alpha
Classifier: Intended Audience :: Developers
Classifier: Topic :: Multimedia :: Sound/Audio :: Analysis
Classifier: Programming Language :: Python :: 3
Classifier: Programming Language :: Python :: 3.6
Classifier: Programming Language :: Python :: 3.7
Classifier: Programming Language :: Python :: 3.8
Classifier: Programming Language :: Python :: 3.9
Classifier: Programming Language :: Python :: 3.10
Classifier: Programming Language :: Python :: 3.11
Classifier: Programming Language :: Python :: 3.12
License-File: LICENSE.md
Requires-Dist: numpy>=1.17
Requires-Dist: numba>=0.53
Requires-Dist: importlib_resources; python_version < "3.9"
Provides-Extra: docs
Requires-Dist: numpydoc; extra == "docs"
Requires-Dist: sphinx!=1.3.1; extra == "docs"
Provides-Extra: tests
Requires-Dist: pytest<8; extra == "tests"
Requires-Dist: pytest-cov; extra == "tests"
Requires-Dist: scipy>=1.1; extra == "tests"
Provides-Extra: design
Requires-Dist: optuna>=2.10.0; extra == "design"
